{"content":[{"id":"64b72af7","settings":{"flex_direction":"row","padding":{"unit":"px","top":"0","right":"0","bottom":"0","left":"0","isLinked":false},"margin":{"unit":"px","top":"60","right":"0","bottom":"30","left":"0","isLinked":false},"css_classes":"contact-information","flex_direction_tablet_extra":"row","padding_tablet_extra":{"unit":"px","top":"0","right":"40","bottom":"0","left":"40","isLinked":false},"padding_mobile_extra":{"unit":"px","top":"0","right":"0","bottom":"0","left":"0","isLinked":false},"boxed_width":{"unit":"px","size":1470,"sizes":[]},"flex_gap":{"unit":"px","size":0,"sizes":[],"column":"0","row":"0","isLinked":true},"flex_direction_mobile_extra":"column"},"elements":[{"id":"f58fbe0","settings":{"content_width":"full","padding":{"unit":"px","top":"0","right":"15","bottom":"0","left":"15","isLinked":false},"margin":{"unit":"px","top":"0","right":"0","bottom":"30","left":"0","isLinked":false},"width_tablet_extra":{"unit":"%","size":100,"sizes":[]},"width_tablet":{"unit":"%","size":"","sizes":[]},"width_mobile_extra":{"unit":"%","size":"","sizes":[]},"width_mobile":{"unit":"%","size":"","sizes":[]},"flex_gap":{"column":"0","row":"0","isLinked":false,"unit":"px","size":0}},"elements":[{"id":"29f57b63","settings":{"list_text_info":[{"_id":"82c86a6","text":"Location","link_text_tag":"#","text_margin":{"unit":"px","top":"0","right":"0","bottom":"015","left":"0","isLinked":false},"text_typography_typography":"custom"},{"_id":"9d0ccc6","text":"Store : <span> C-301 Bhavani Complex Nr. Gajera circle Opp. Saibaba Petrol Pump Katargam Surat-395004<\/span>","text_tag":"p","link_text_tag":"#","text_margin":{"unit":"px","top":"0","right":"0","bottom":"10","left":"0","isLinked":false},"text_typography_font_size":{"unit":"px","size":18,"sizes":[]},"text_typography_font_weight":"500"}],"icon":{"value":" las la-map-marker-alt","library":"lineicons"},"container_flexgap_item":{"unit":"px","size":20,"sizes":[]},"info_container_flex_flex_direction":"column","container_flex_margin_css":{"unit":"px","top":"0","right":"0","bottom":"0","left":"0","isLinked":false},"style_icon_size_css_tablet_extra":{"unit":"px","size":36,"sizes":[]},"list_icon":[],"menu_vertical_title":"Title text","menu_vertical_list":[]},"elements":[],"isInner":false,"widgetType":"bzotech_info_box_global","elType":"widget"}],"isInner":true,"elType":"container"},{"id":"664b6f7","settings":{"content_width":"full","margin":{"unit":"px","top":"0","right":"0","bottom":"30","left":"0","isLinked":false},"padding":{"unit":"px","top":"0","right":"15","bottom":"0","left":"15","isLinked":false},"width_tablet_extra":{"unit":"%","size":100,"sizes":[]},"width_tablet":{"unit":"%","size":"","sizes":[]},"width_mobile_extra":{"unit":"%","size":"","sizes":[]},"width_mobile":{"unit":"%","size":"","sizes":[]},"flex_gap":{"column":"0","row":"0","isLinked":false,"unit":"px","size":0}},"elements":[{"id":"1b3d4a47","settings":{"list_text_info":[{"_id":"82c86a6","text":"Contact","link_text_tag":"#","text_margin":{"unit":"px","top":"0","right":"0","bottom":"015","left":"0","isLinked":false},"text_typography_typography":"custom"},{"_id":"9d0ccc6","text":"Mobile: <a href=\"tel:+91-8780389067\">+91-8780389067<\/a>","text_tag":"p","link_text_tag":"#","text_margin":{"unit":"px","top":"0","right":"0","bottom":"10","left":"0","isLinked":false},"text_typography_font_size":{"unit":"px","size":18,"sizes":[]},"text_typography_font_weight":"500"},{"text":"Email: <a href=\"lvstrendz.info@gmail.com\">lvstrendz.info@gmail.com<\/a>","text_tag":"p","link_text_tag":"#","text_margin":{"unit":"px","top":"0","right":"0","bottom":"10","left":"0","isLinked":false},"_id":"1a40376"}],"icon":{"value":" las la-phone-volume","library":"lineicons"},"container_flexgap_item":{"unit":"px","size":20,"sizes":[]},"info_container_flex_flex_direction":"column","container_flex_margin_css":{"unit":"px","top":"0","right":"0","bottom":"0","left":"0","isLinked":false},"style_icon_size_css_tablet_extra":{"unit":"px","size":36,"sizes":[]},"list_icon":[],"menu_vertical_title":"Title text","menu_vertical_list":[]},"elements":[],"isInner":false,"widgetType":"bzotech_info_box_global","elType":"widget"}],"isInner":true,"elType":"container"},{"id":"b101f90","settings":{"content_width":"full","margin":{"unit":"px","top":"0","right":"0","bottom":"30","left":"0","isLinked":false},"padding":{"unit":"px","top":"0","right":"15","bottom":"0","left":"15","isLinked":false},"width_tablet_extra":{"unit":"%","size":100,"sizes":[]},"width_tablet":{"unit":"%","size":"","sizes":[]},"width_mobile_extra":{"unit":"%","size":"","sizes":[]},"width_mobile":{"unit":"%","size":"","sizes":[]},"flex_gap":{"column":"0","row":"0","isLinked":false,"unit":"px","size":0}},"elements":[{"id":"55480da","settings":{"list_text_info":[{"_id":"82c86a6","text":"Open Hour","link_text_tag":"#","text_margin":{"unit":"px","top":"0","right":"0","bottom":"015","left":"0","isLinked":false},"text_typography_typography":"custom"},{"_id":"9d0ccc6","text":"Monday \u2013 Sunday: 8:00 am \u2013 10:00pm","text_tag":"p","link_text_tag":"#","text_margin":{"unit":"px","top":"0","right":"0","bottom":"10","left":"0","isLinked":false},"text_typography_font_size":{"unit":"px","size":18,"sizes":[]},"text_typography_font_weight":"500"}],"icon":{"value":" las la-clock","library":"lineicons"},"container_flexgap_item":{"unit":"px","size":20,"sizes":[]},"info_container_flex_flex_direction":"column","container_flex_margin_css":{"unit":"px","top":"0","right":"0","bottom":"0","left":"0","isLinked":false},"container_flexgap_item_tablet_extra":{"unit":"px","size":10,"sizes":[]},"style_icon_size_css_tablet_extra":{"unit":"px","size":36,"sizes":[]},"list_icon":[],"menu_vertical_title":"Title text","menu_vertical_list":[]},"elements":[],"isInner":false,"widgetType":"bzotech_info_box_global","elType":"widget"}],"isInner":true,"elType":"container"}],"isInner":false,"elType":"container"},{"id":"564488c5","settings":{"flex_direction":"row","content_width":"full","margin":{"unit":"px","top":"0","right":"0","bottom":"60","left":"0","isLinked":false},"padding":{"unit":"px","top":"0","right":"0","bottom":"0","left":"0","isLinked":false},"margin_mobile":{"unit":"px","top":"0","right":"0","bottom":"50","left":"0","isLinked":false},"flex_gap":{"column":"0","row":"0","isLinked":false,"unit":"px","size":0}},"elements":[{"id":"562ac810","settings":{"address":"Bhavani Complex, Mahavir Nagar Society, Vishal Nagar, Surat, Gujarat 395004","zoom":{"unit":"px","size":14,"sizes":[]},"height":{"unit":"px","size":535,"sizes":[]},"css_filters_brightness":{"unit":"px","size":111,"sizes":[]},"css_filters_contrast":{"unit":"px","size":64,"sizes":[]},"css_filters_saturate":{"unit":"px","size":82,"sizes":[]}},"elements":[],"isInner":false,"widgetType":"google_maps","elType":"widget"}],"isInner":false,"elType":"container"},{"id":"39e25fcb","settings":{"flex_direction":"row","margin":{"unit":"px","top":"0","right":"0","bottom":"60","left":"0","isLinked":false},"padding":{"unit":"px","top":"0","right":"0","bottom":"0","left":"0","isLinked":false},"css_classes":"box-contact-page","margin_mobile":{"unit":"px","top":"0","right":"0","bottom":"050","left":"0","isLinked":false},"boxed_width":{"unit":"px","size":1470,"sizes":[]},"flex_gap":{"unit":"px","size":0,"sizes":[],"column":"0","row":"0","isLinked":true}},"elements":[{"id":"3f602bdd","settings":{"content_width":"full","padding":{"unit":"px","top":"0","right":"15","bottom":"0","left":"15","isLinked":false}},"elements":[{"id":"7573f6a3","settings":{"background_background":"classic","background_color":"#F5F5F5","padding":{"unit":"px","top":"0","right":"0","bottom":"0","left":"0","isLinked":false},"boxed_width":{"unit":"px","size":1560,"sizes":[]},"flex_gap":{"unit":"px","size":0,"sizes":[],"column":"0","row":"0","isLinked":true}},"elements":[{"id":"7ff1a264","settings":{"header_style":"style1","title":"Send A Message","align":"center","typography_typography":"custom","typography_font_size":{"unit":"px","size":30,"sizes":[]},"typography_font_size_mobile_extra":{"unit":"px","size":28,"sizes":[]},"typography_font_weight":"600","css_border_elementor_border":"solid","css_border_elementor_width":{"unit":"px","top":"0","right":"0","bottom":"1","left":"0","isLinked":false},"css_border_elementor_color":"#D6D6D6","title_padding":{"unit":"px","top":"40","right":"0","bottom":"20","left":"0","isLinked":false},"_margin":{"unit":"px","top":"0","right":"0","bottom":"40","left":"0","isLinked":false}},"elements":[],"isInner":false,"widgetType":"bzotech-heading-global","elType":"widget"},{"id":"635bc5e9","settings":{"title":"Add Your Heading Text Here","editor":"<p>[contact-form-7 id=\"5035\" title=\"Contact page\"]<\/p>","align":"center","_margin":{"unit":"px","top":"0","right":"0","bottom":"0","left":"0","isLinked":false},"_padding":{"unit":"px","top":"0","right":"40","bottom":"40","left":"40","isLinked":false},"_padding_mobile":{"unit":"px","top":"0","right":"20","bottom":"40","left":"20","isLinked":false},"_css_classes":"box-contact-form"},"elements":[],"isInner":false,"widgetType":"bzotech-heading-global","elType":"widget"}],"isInner":true,"elType":"container"}],"isInner":true,"elType":"container"}],"isInner":false,"elType":"container"}],"settings":{"template":"elementor-template.php"},"metadata":{"redux-metabox-section":"0_box_redux-bzotech_theme_option-metabox-bzotech_sidebar_option","bzotech_header_page":"","bzotech_footer_page":"","bzotech_sidebar_position":"","bzotech_select_sidebar":"","bzotech_sidebar_style":"","before_append":"7748","after_append":"","show_title_page":"1","post_single_page_share":"","body_bg":"a:3:{s:5:\"color\";s:0:\"\";s:5:\"alpha\";s:1:\"1\";s:4:\"rgba\";s:0:\"\";}","main_color":"a:3:{s:5:\"color\";s:0:\"\";s:5:\"alpha\";s:1:\"1\";s:4:\"rgba\";s:0:\"\";}","main_color2":"a:3:{s:5:\"color\";s:0:\"\";s:5:\"alpha\";s:1:\"1\";s:4:\"rgba\";s:0:\"\";}","bzotech_page_style":"","container_width":"","add_class_body_page":"","rs_page_bg_color":""}}